ecs_deploy/__init__.py
ecs_deploy/cli.py
ecs_deploy/ecs.py
ecs_deploy/newrelic.py
ecs_deploy/slack.py
ecs_deploy-1.15.2.dist-info/licenses/LICENSE.rst
ecs_deploy-1.15.2.dist-info/METADATA
ecs_deploy-1.15.2.dist-info/WHEEL
ecs_deploy-1.15.2.dist-info/entry_points.txt
ecs_deploy-1.15.2.dist-info/top_level.txt
ecs_deploy-1.15.2.dist-info/RECORD
