Metadata-Version: 2.4
Name: ecs-deploy
Version: 1.15.2
Summary: Powerful CLI tool to simplify Amazon ECS deployments, rollbacks & scaling
Home-page: https://github.com/fabfuel/ecs-deploy
Download-URL: https://github.com/fabfuel/ecs-deploy/archive/1.15.2.tar.gz
Author: Fabian Fuelling
Author-email: pypi@fabfuel.de
License: BSD-3-Clause
Platform: any
Classifier: Environment :: Console
Classifier: Intended Audience :: Developers
Classifier: License :: OSI Approved :: BSD License
Classifier: Operating System :: POSIX
Classifier: Operating System :: MacOS
Classifier: Operating System :: Unix
Classifier: Programming Language :: Python
Classifier: Programming Language :: Python :: 3
Classifier: Topic :: Software Development :: Libraries :: Python Modules
License-File: LICENSE.rst
Requires-Dist: click<9,>=7.1.2
Requires-Dist: click-log==0.3.2
Requires-Dist: botocore>=1.32.6
Requires-Dist: boto3>=1.29.6
Requires-Dist: future
Requires-Dist: requests<2.30.0
Requires-Dist: dictdiffer>=0.9.0
Dynamic: author
Dynamic: author-email
Dynamic: classifier
Dynamic: description
Dynamic: download-url
Dynamic: home-page
Dynamic: license
Dynamic: license-file
Dynamic: platform
Dynamic: requires-dist
Dynamic: summary
